processflow/__init__.py
processflow/activity.py
processflow/bpmn.py
processflow/colourtheme.py
processflow/constants.py
processflow/coordinate.py
processflow/drawio.py
processflow/event.py
processflow/footer.py
processflow/gateway.py
processflow/helper.py
processflow/lane.py
processflow/layout.py
processflow/painter.py
processflow/pool.py
processflow/processmap.py
processflow/shape.py
processflow/text2diagram.py
processflow/title.py
processflow/version.py
processflow-1.0.1.dist-info/LICENSE
processflow-1.0.1.dist-info/METADATA
processflow-1.0.1.dist-info/WHEEL
processflow-1.0.1.dist-info/top_level.txt
processflow-1.0.1.dist-info/zip-safe
processflow-1.0.1.dist-info/RECORD
